README.md
setup.py
rake/__init__.py
rake/rake.py
rake_keyword.egg-info/PKG-INFO
rake_keyword.egg-info/SOURCES.txt
rake_keyword.egg-info/dependency_links.txt
rake_keyword.egg-info/top_level.txt