Metadata-Version: 2.1
Name: rake-keyword
Version: 0.0.1
Summary: Implementation of RAKE - Rapid Automatic Keyword Extraction
Home-page: https://github.com/u-prashant/RAKE
Author: Prashant Upadhyay
Author-email: prashant.u@hotmail.com
License: UNKNOWN
Platform: UNKNOWN
Classifier: Programming Language :: Python :: 3
Classifier: License :: OSI Approved :: MIT License
Classifier: Operating System :: OS Independent
Requires-Python: >=3.6
